setup.py
src/dt_computer_vision/__init__.py
src/dt_computer_vision/anti_instagram/__init__.py
src/dt_computer_vision/anti_instagram/anti_instagram.py
src/dt_computer_vision/camera/__init__.py
src/dt_computer_vision/camera/homography.py
src/dt_computer_vision/camera/types.py
src/dt_computer_vision/camera/utils.py
src/dt_computer_vision/camera/calibration/__init__.py
src/dt_computer_vision/camera/calibration/extrinsics/__init__.py
src/dt_computer_vision/camera/calibration/extrinsics/boards.py
src/dt_computer_vision/camera/calibration/extrinsics/chessboard.py
src/dt_computer_vision/camera/calibration/extrinsics/exceptions.py
src/dt_computer_vision/camera/calibration/extrinsics/ransac.py
src/dt_computer_vision/camera/calibration/extrinsics/rendering.py
src/dt_computer_vision/camera/calibration/extrinsics/assets/gui_active.png
src/dt_computer_vision/camera/calibration/extrinsics/assets/gui_inactive.png
src/dt_computer_vision/camera/calibration/extrinsics/assets/validation_gui.png
src/dt_computer_vision/ground_projection/__init__.py
src/dt_computer_vision/ground_projection/ground_projector.py
src/dt_computer_vision/ground_projection/rendering.py
src/dt_computer_vision/ground_projection/types.py
src/dt_computer_vision/line_detection/__init__.py
src/dt_computer_vision/line_detection/line_detector.py
src/dt_computer_vision/line_detection/rendering.py
src/dt_computer_vision/line_detection/types.py
src/dt_computer_vision/optical_flow/__init__.py
src/dt_computer_vision/optical_flow/optical_flow.py
src/lib_dt_computer_vision.egg-info/PKG-INFO
src/lib_dt_computer_vision.egg-info/SOURCES.txt
src/lib_dt_computer_vision.egg-info/dependency_links.txt
src/lib_dt_computer_vision.egg-info/requires.txt
src/lib_dt_computer_vision.egg-info/top_level.txt