Metadata-Version: 2.1
Name: lib-dt-computer-vision
Version: 0.2.1
Home-page: http://github.com/duckietown/lib-dt-computer-vision
Author: Andrea F. Daniele
Author-email: afdaniele@duckietown.com
Requires-Dist: opencv-python-headless<=4.9.0.80
Requires-Dist: numpy<=1.26.4
Requires-Dist: requests<=2.31.0
Provides-Extra: test
Requires-Dist: pytest; extra == "test"
Requires-Dist: pytest-cov; extra == "test"
